<?xml version="1.0" encoding="utf-8"?>
<clothing-items>
 <clothing>
  <id>
   984716340
  </id>
  <name>
   Vans Shirt B-7063
  </name>
  <category>
   Shirt
  </category>
  <size>
   L
  </size>
  <color>
   Голубой
  </color>
  <material>
   Шелк
  </material>
  <price>
   375276
  </price>
  <rating>
   2.14
  </rating>
  <reviews>
   738346
  </reviews>
  <new>
   -
  </new>
  <sporty>
   yes
  </sporty>
 </clothing>
 <clothing>
  <id>
   925294728
  </id>
  <name>
   DC Hat N-1014
  </name>
  <category>
   Hat
  </category>
  <size>
   XL
  </size>
  <color>
   Зеленый
  </color>
  <material>
   Нейлон
  </material>
  <price>
   223740
  </price>
  <rating>
   2.9
  </rating>
  <reviews>
   66588
  </reviews>
  <new>
   -
  </new>
  <sporty>
   no
  </sporty>
 </clothing>
 <clothing>
  <id>
   813596455
  </id>
  <name>
   Reebok Handbags Q-1337
  </name>
  <category>
   Handbags
  </category>
  <size>
   XXL
  </size>
  <color>
   Голубой
  </color>
  <material>
   Шерсть
  </material>
  <price>
   816745
  </price>
  <rating>
   4.0
  </rating>
  <reviews>
   799682
  </reviews>
  <new>
   +
  </new>
  <exclusive>
   no
  </exclusive>
  <sporty>
   yes
  </sporty>
 </clothing>
 <clothing>
  <id>
   794783485
  </id>
  <name>
   Under Armour Blouse M-4696
  </name>
  <category>
   Blouse
  </category>
  <size>
   L
  </size>
  <color>
   Фиолетовый
  </color>
  <material>
   Шерсть
  </material>
  <price>
   484636
  </price>
  <rating>
   3.86
  </rating>
  <reviews>
   18082
  </reviews>
  <sporty>
   no
  </sporty>
 </clothing>
 <clothing>
  <id>
   692366003
  </id>
  <name>
   Ellesse T-shirt I-2660
  </name>
  <category>
   T-shirt
  </category>
  <size>
   L
  </size>
  <color>
   Зеленый
  </color>
  <material>
   Нейлон
  </material>
  <price>
   734812
  </price>
  <rating>
   2.06
  </rating>
  <reviews>
   297487
  </reviews>
  <sporty>
   no
  </sporty>
 </clothing>
 <clothing>
  <id>
   705968698
  </id>
  <name>
   Under Armour Shirt H-1506
  </name>
  <category>
   Shirt
  </category>
  <size>
   M
  </size>
  <color>
   Синий
  </color>
  <material>
   Нейлон
  </material>
  <price>
   883256
  </price>
  <rating>
   1.31
  </rating>
  <reviews>
   987322
  </reviews>
  <new>
   +
  </new>
  <sporty>
   no
  </sporty>
 </clothing>
 <clothing>
  <id>
   916098433
  </id>
  <name>
   Ellesse Handbags Q-9560
  </name>
  <category>
   Handbags
  </category>
  <size>
   L
  </size>
  <color>
   Оранжевый
  </color>
  <material>
   Вискоза
  </material>
  <price>
   552303
  </price>
  <rating>
   1.02
  </rating>
  <reviews>
   363667
  </reviews>
 </clothing>
 <clothing>
  <id>
   365918416
  </id>
  <name>
   Puma Jacket E-1685
  </name>
  <category>
   Jacket
  </category>
  <size>
   M
  </size>
  <color>
   Оранжевый
  </color>
  <material>
   Шелк
  </material>
  <price>
   713817
  </price>
  <rating>
   1.94
  </rating>
  <reviews>
   520283
  </reviews>
  <exclusive>
   yes
  </exclusive>
 </clothing>
 <clothing>
  <id>
   528934787
  </id>
  <name>
   Under Armour Jacket C-4516
  </name>
  <category>
   Jacket
  </category>
  <size>
   M
  </size>
  <color>
   Голубой
  </color>
  <material>
   Нейлон
  </material>
  <price>
   806033
  </price>
  <rating>
   3.94
  </rating>
  <reviews>
   185789
  </reviews>
  <new>
   -
  </new>
  <exclusive>
   yes
  </exclusive>
 </clothing>
 <clothing>
  <id>
   205164582
  </id>
  <name>
   Addidas Hat V-2937
  </name>
  <category>
   Hat
  </category>
  <size>
   M
  </size>
  <color>
   Синий
  </color>
  <material>
   Нейлон
  </material>
  <price>
   455797
  </price>
  <rating>
   2.99
  </rating>
  <reviews>
   641464
  </reviews>
  <new>
   -
  </new>
  <exclusive>
   no
  </exclusive>
  <sporty>
   no
  </sporty>
 </clothing>
 <clothing>
  <id>
   791491551
  </id>
  <name>
   Converse Blouse P-1620
  </name>
  <category>
   Blouse
  </category>
  <size>
   M
  </size>
  <color>
   Оранжевый
  </color>
  <material>
   Лен
  </material>
  <price>
   239974
  </price>
  <rating>
   4.87
  </rating>
  <reviews>
   988572
  </reviews>
  <exclusive>
   yes
  </exclusive>
  <sporty>
   no
  </sporty>
 </clothing>
 <clothing>
  <id>
   859328075
  </id>
  <name>
   Addidas Skirt C-9941
  </name>
  <category>
   Skirt
  </category>
  <size>
   S
  </size>
  <color>
   Голубой
  </color>
  <material>
   Вискоза
  </material>
  <price>
   405505
  </price>
  <rating>
   4.57
  </rating>
  <reviews>
   60150
  </reviews>
 </clothing>
 <clothing>
  <id>
   304489153
  </id>
  <name>
   DC Hat A-4367
  </name>
  <category>
   Hat
  </category>
  <size>
   XXL
  </size>
  <color>
   Синий
  </color>
  <material>
   Хлопок
  </material>
  <price>
   694637
  </price>
  <rating>
   1.07
  </rating>
  <reviews>
   427016
  </reviews>
  <new>
   -
  </new>
  <sporty>
   no
  </sporty>
 </clothing>
 <clothing>
  <id>
   800915443
  </id>
  <name>
   Brooks Jacket A-3329
  </name>
  <category>
   Jacket
  </category>
  <size>
   L
  </size>
  <color>
   Желтый
  </color>
  <material>
   Полиэстер
  </material>
  <price>
   278459
  </price>
  <rating>
   4.81
  </rating>
  <reviews>
   577835
  </reviews>
  <new>
   -
  </new>
  <sporty>
   yes
  </sporty>
 </clothing>
 <clothing>
  <id>
   477587928
  </id>
  <name>
   Puma Belts Z-7712
  </name>
  <category>
   Belts
  </category>
  <size>
   M
  </size>
  <color>
   Желтый
  </color>
  <material>
   Полиэстер
  </material>
  <price>
   914157
  </price>
  <rating>
   2.12
  </rating>
  <reviews>
   637495
  </reviews>
  <new>
   +
  </new>
  <exclusive>
   no
  </exclusive>
  <sporty>
   yes
  </sporty>
 </clothing>
 <clothing>
  <id>
   404420883
  </id>
  <name>
   Brooks T-shirt J-6560
  </name>
  <category>
   T-shirt
  </category>
  <size>
   L
  </size>
  <color>
   Фиолетовый
  </color>
  <material>
   Лен
  </material>
  <price>
   788940
  </price>
  <rating>
   1.34
  </rating>
  <reviews>
   467593
  </reviews>
  <new>
   -
  </new>
  <exclusive>
   no
  </exclusive>
  <sporty>
   no
  </sporty>
 </clothing>
 <clothing>
  <id>
   615293852
  </id>
  <name>
   Asics Pants C-1027
  </name>
  <category>
   Pants
  </category>
  <size>
   XL
  </size>
  <color>
   Оранжевый
  </color>
  <material>
   Вискоза
  </material>
  <price>
   859015
  </price>
  <rating>
   1.07
  </rating>
  <reviews>
   263834
  </reviews>
  <new>
   +
  </new>
 </clothing>
 <clothing>
  <id>
   649675056
  </id>
  <name>
   DC Jacket S-3469
  </name>
  <category>
   Jacket
  </category>
  <size>
   L
  </size>
  <color>
   Красный
  </color>
  <material>
   Кожа
  </material>
  <price>
   754084
  </price>
  <rating>
   3.98
  </rating>
  <reviews>
   553446
  </reviews>
  <new>
   -
  </new>
  <sporty>
   no
  </sporty>
 </clothing>
 <clothing>
  <id>
   589998624
  </id>
  <name>
   Reebok Jacket V-1979
  </name>
  <category>
   Jacket
  </category>
  <size>
   S
  </size>
  <color>
   Синий
  </color>
  <material>
   Шерсть
  </material>
  <price>
   848133
  </price>
  <rating>
   1.48
  </rating>
  <reviews>
   446336
  </reviews>
 </clothing>
 <clothing>
  <id>
   656061747
  </id>
  <name>
   Under Armour Socks B-4946
  </name>
  <category>
   Socks
  </category>
  <size>
   XL
  </size>
  <color>
   Синий
  </color>
  <material>
   Хлопок
  </material>
  <price>
   431708
  </price>
  <rating>
   2.3
  </rating>
  <reviews>
   967639
  </reviews>
  <new>
   +
  </new>
  <exclusive>
   no
  </exclusive>
  <sporty>
   yes
  </sporty>
 </clothing>
 <clothing>
  <id>
   199841651
  </id>
  <name>
   New Balance Jeans H-4843
  </name>
  <category>
   Jeans
  </category>
  <size>
   M
  </size>
  <color>
   Желтый
  </color>
  <material>
   Хлопок
  </material>
  <price>
   977603
  </price>
  <rating>
   3.76
  </rating>
  <reviews>
   778341
  </reviews>
  <new>
   +
  </new>
 </clothing>
 <clothing>
  <id>
   243179492
  </id>
  <name>
   Fila Shoes M-5094
  </name>
  <category>
   Shoes
  </category>
  <size>
   M
  </size>
  <color>
   Синий
  </color>
  <material>
   Лен
  </material>
  <price>
   907202
  </price>
  <rating>
   2.25
  </rating>
  <reviews>
   296316
  </reviews>
  <exclusive>
   no
  </exclusive>
  <sporty>
   yes
  </sporty>
 </clothing>
 <clothing>
  <id>
   356025966
  </id>
  <name>
   Asics Shoes L-6604
  </name>
  <category>
   Shoes
  </category>
  <size>
   S
  </size>
  <color>
   Оранжевый
  </color>
  <material>
   Вискоза
  </material>
  <price>
   762571
  </price>
  <rating>
   2.89
  </rating>
  <reviews>
   180133
  </reviews>
  <new>
   -
  </new>
  <exclusive>
   yes
  </exclusive>
 </clothing>
 <clothing>
  <id>
   669375990
  </id>
  <name>
   Vans Socks Y-7429
  </name>
  <category>
   Socks
  </category>
  <size>
   L
  </size>
  <color>
   Оранжевый
  </color>
  <material>
   Вискоза
  </material>
  <price>
   612492
  </price>
  <rating>
   4.25
  </rating>
  <reviews>
   945334
  </reviews>
  <sporty>
   yes
  </sporty>
 </clothing>
 <clothing>
  <id>
   732818473
  </id>
  <name>
   Lacoste Gloves O-6499
  </name>
  <category>
   Gloves
  </category>
  <size>
   XXL
  </size>
  <color>
   Красный
  </color>
  <material>
   Шелк
  </material>
  <price>
   799243
  </price>
  <rating>
   4.73
  </rating>
  <reviews>
   244842
  </reviews>
  <exclusive>
   no
  </exclusive>
  <sporty>
   no
  </sporty>
 </clothing>
 <clothing>
  <id>
   511314081
  </id>
  <name>
   Lacoste Shoes U-2683
  </name>
  <category>
   Shoes
  </category>
  <size>
   XXL
  </size>
  <color>
   Оранжевый
  </color>
  <material>
   Хлопок
  </material>
  <price>
   474376
  </price>
  <rating>
   4.29
  </rating>
  <reviews>
   77303
  </reviews>
  <new>
   +
  </new>
  <exclusive>
   yes
  </exclusive>
 </clothing>
 <clothing>
  <id>
   608121427
  </id>
  <name>
   Brooks Umbrellas I-9744
  </name>
  <category>
   Umbrellas
  </category>
  <size>
   M
  </size>
  <color>
   Синий
  </color>
  <material>
   Кожа
  </material>
  <price>
   682847
  </price>
  <rating>
   1.18
  </rating>
  <reviews>
   61997
  </reviews>
  <exclusive>
   no
  </exclusive>
 </clothing>
 <clothing>
  <id>
   224744608
  </id>
  <name>
   Ellesse Shirt X-3328
  </name>
  <category>
   Shirt
  </category>
  <size>
   M
  </size>
  <color>
   Красный
  </color>
  <material>
   Хлопок
  </material>
  <price>
   465433
  </price>
  <rating>
   4.52
  </rating>
  <reviews>
   159432
  </reviews>
  <new>
   -
  </new>
  <sporty>
   no
  </sporty>
 </clothing>
 <clothing>
  <id>
   954330999
  </id>
  <name>
   Converse Skirt F-7234
  </name>
  <category>
   Skirt
  </category>
  <size>
   XXL
  </size>
  <color>
   Фиолетовый
  </color>
  <material>
   Кожа
  </material>
  <price>
   738676
  </price>
  <rating>
   2.02
  </rating>
  <reviews>
   760235
  </reviews>
  <exclusive>
   no
  </exclusive>
  <sporty>
   yes
  </sporty>
 </clothing>
 <clothing>
  <id>
   680868967
  </id>
  <name>
   Brooks Shirt S-9284
  </name>
  <category>
   Shirt
  </category>
  <size>
   S
  </size>
  <color>
   Желтый
  </color>
  <material>
   Хлопок
  </material>
  <price>
   531886
  </price>
  <rating>
   1.81
  </rating>
  <reviews>
   605735
  </reviews>
  <new>
   +
  </new>
  <exclusive>
   no
  </exclusive>
 </clothing>
 <clothing>
  <id>
   303201408
  </id>
  <name>
   PleinSport Gloves K-1466
  </name>
  <category>
   Gloves
  </category>
  <size>
   L
  </size>
  <color>
   Голубой
  </color>
  <material>
   Хлопок
  </material>
  <price>
   865068
  </price>
  <rating>
   3.52
  </rating>
  <reviews>
   211898
  </reviews>
  <new>
   +
  </new>
 </clothing>
 <clothing>
  <id>
   590502013
  </id>
  <name>
   New Balance Gloves V-5154
  </name>
  <category>
   Gloves
  </category>
  <size>
   XL
  </size>
  <color>
   Желтый
  </color>
  <material>
   Нейлон
  </material>
  <price>
   107408
  </price>
  <rating>
   1.43
  </rating>
  <reviews>
   22324
  </reviews>
  <new>
   +
  </new>
  <exclusive>
   no
  </exclusive>
 </clothing>
 <clothing>
  <id>
   400875445
  </id>
  <name>
   PleinSport Gloves R-1211
  </name>
  <category>
   Gloves
  </category>
  <size>
   L
  </size>
  <color>
   Синий
  </color>
  <material>
   Хлопок
  </material>
  <price>
   674456
  </price>
  <rating>
   1.51
  </rating>
  <reviews>
   466279
  </reviews>
  <sporty>
   no
  </sporty>
 </clothing>
 <clothing>
  <id>
   169039703
  </id>
  <name>
   DC Pants Q-3176
  </name>
  <category>
   Pants
  </category>
  <size>
   XL
  </size>
  <color>
   Желтый
  </color>
  <material>
   Лен
  </material>
  <price>
   225171
  </price>
  <rating>
   4.56
  </rating>
  <reviews>
   596638
  </reviews>
  <new>
   -
  </new>
  <exclusive>
   yes
  </exclusive>
 </clothing>
 <clothing>
  <id>
   287132985
  </id>
  <name>
   Nike Skirt P-4293
  </name>
  <category>
   Skirt
  </category>
  <size>
   XXL
  </size>
  <color>
   Зеленый
  </color>
  <material>
   Хлопок
  </material>
  <price>
   679088
  </price>
  <rating>
   2.67
  </rating>
  <reviews>
   334079
  </reviews>
  <new>
   -
  </new>
  <exclusive>
   yes
  </exclusive>
 </clothing>
</clothing-items>
