<?xml version="1.0" encoding="utf-8"?>
<clothing-items>
 <clothing>
  <id>
   459620857
  </id>
  <name>
   DC Skirt K-7613
  </name>
  <category>
   Skirt
  </category>
  <size>
   M
  </size>
  <color>
   Фиолетовый
  </color>
  <material>
   Шелк
  </material>
  <price>
   159402
  </price>
  <rating>
   1.74
  </rating>
  <reviews>
   136662
  </reviews>
  <exclusive>
   no
  </exclusive>
  <sporty>
   yes
  </sporty>
 </clothing>
 <clothing>
  <id>
   199194635
  </id>
  <name>
   Fila Shoes E-8248
  </name>
  <category>
   Shoes
  </category>
  <size>
   XL
  </size>
  <color>
   Синий
  </color>
  <material>
   Хлопок
  </material>
  <price>
   176528
  </price>
  <rating>
   3.26
  </rating>
  <reviews>
   376908
  </reviews>
  <new>
   +
  </new>
  <exclusive>
   yes
  </exclusive>
  <sporty>
   yes
  </sporty>
 </clothing>
 <clothing>
  <id>
   840335368
  </id>
  <name>
   PleinSport Belts K-6128
  </name>
  <category>
   Belts
  </category>
  <size>
   XXL
  </size>
  <color>
   Красный
  </color>
  <material>
   Кожа
  </material>
  <price>
   547875
  </price>
  <rating>
   2.76
  </rating>
  <reviews>
   632410
  </reviews>
  <exclusive>
   yes
  </exclusive>
 </clothing>
 <clothing>
  <id>
   295236025
  </id>
  <name>
   PleinSport Skirt Q-3315
  </name>
  <category>
   Skirt
  </category>
  <size>
   M
  </size>
  <color>
   Желтый
  </color>
  <material>
   Нейлон
  </material>
  <price>
   541824
  </price>
  <rating>
   4.91
  </rating>
  <reviews>
   840815
  </reviews>
  <new>
   +
  </new>
  <exclusive>
   yes
  </exclusive>
 </clothing>
 <clothing>
  <id>
   334002088
  </id>
  <name>
   Nike Handbags I-8891
  </name>
  <category>
   Handbags
  </category>
  <size>
   L
  </size>
  <color>
   Голубой
  </color>
  <material>
   Шелк
  </material>
  <price>
   495876
  </price>
  <rating>
   2.74
  </rating>
  <reviews>
   628282
  </reviews>
  <sporty>
   yes
  </sporty>
 </clothing>
 <clothing>
  <id>
   219941818
  </id>
  <name>
   PleinSport Hat K-6082
  </name>
  <category>
   Hat
  </category>
  <size>
   XL
  </size>
  <color>
   Оранжевый
  </color>
  <material>
   Полиэстер
  </material>
  <price>
   172160
  </price>
  <rating>
   2.22
  </rating>
  <reviews>
   289870
  </reviews>
  <exclusive>
   no
  </exclusive>
  <sporty>
   no
  </sporty>
 </clothing>
 <clothing>
  <id>
   934202229
  </id>
  <name>
   Ellesse Sweater A-3481
  </name>
  <category>
   Sweater
  </category>
  <size>
   XL
  </size>
  <color>
   Голубой
  </color>
  <material>
   Вискоза
  </material>
  <price>
   726410
  </price>
  <rating>
   4.19
  </rating>
  <reviews>
   308980
  </reviews>
  <exclusive>
   no
  </exclusive>
 </clothing>
 <clothing>
  <id>
   886298869
  </id>
  <name>
   Converse Socks I-3849
  </name>
  <category>
   Socks
  </category>
  <size>
   XXL
  </size>
  <color>
   Зеленый
  </color>
  <material>
   Вискоза
  </material>
  <price>
   858441
  </price>
  <rating>
   1.3
  </rating>
  <reviews>
   360760
  </reviews>
  <new>
   +
  </new>
  <exclusive>
   no
  </exclusive>
  <sporty>
   no
  </sporty>
 </clothing>
 <clothing>
  <id>
   793722087
  </id>
  <name>
   PleinSport Jeans L-1269
  </name>
  <category>
   Jeans
  </category>
  <size>
   M
  </size>
  <color>
   Зеленый
  </color>
  <material>
   Шелк
  </material>
  <price>
   498860
  </price>
  <rating>
   1.81
  </rating>
  <reviews>
   729551
  </reviews>
  <new>
   -
  </new>
  <exclusive>
   yes
  </exclusive>
  <sporty>
   yes
  </sporty>
 </clothing>
 <clothing>
  <id>
   744266987
  </id>
  <name>
   Vans Jeans Z-1148
  </name>
  <category>
   Jeans
  </category>
  <size>
   XXL
  </size>
  <color>
   Желтый
  </color>
  <material>
   Хлопок
  </material>
  <price>
   309455
  </price>
  <rating>
   1.93
  </rating>
  <reviews>
   570747
  </reviews>
  <new>
   -
  </new>
  <exclusive>
   no
  </exclusive>
 </clothing>
 <clothing>
  <id>
   531485031
  </id>
  <name>
   New Balance Blouse K-2151
  </name>
  <category>
   Blouse
  </category>
  <size>
   L
  </size>
  <color>
   Фиолетовый
  </color>
  <material>
   Вискоза
  </material>
  <price>
   662195
  </price>
  <rating>
   1.89
  </rating>
  <reviews>
   794917
  </reviews>
  <exclusive>
   yes
  </exclusive>
  <sporty>
   yes
  </sporty>
 </clothing>
 <clothing>
  <id>
   288298373
  </id>
  <name>
   Addidas Jacket K-8147
  </name>
  <category>
   Jacket
  </category>
  <size>
   S
  </size>
  <color>
   Красный
  </color>
  <material>
   Лен
  </material>
  <price>
   316001
  </price>
  <rating>
   1.29
  </rating>
  <reviews>
   602290
  </reviews>
  <new>
   -
  </new>
  <sporty>
   yes
  </sporty>
 </clothing>
 <clothing>
  <id>
   248077708
  </id>
  <name>
   Converse Dress V-9155
  </name>
  <category>
   Dress
  </category>
  <size>
   XL
  </size>
  <color>
   Фиолетовый
  </color>
  <material>
   Шелк
  </material>
  <price>
   792758
  </price>
  <rating>
   3.12
  </rating>
  <reviews>
   729870
  </reviews>
  <new>
   -
  </new>
  <exclusive>
   yes
  </exclusive>
 </clothing>
 <clothing>
  <id>
   228544169
  </id>
  <name>
   Lacoste Blouse J-6513
  </name>
  <category>
   Blouse
  </category>
  <size>
   XXL
  </size>
  <color>
   Желтый
  </color>
  <material>
   Лен
  </material>
  <price>
   237219
  </price>
  <rating>
   4.4
  </rating>
  <reviews>
   152028
  </reviews>
  <exclusive>
   no
  </exclusive>
 </clothing>
 <clothing>
  <id>
   896450181
  </id>
  <name>
   Converse Handbags G-1717
  </name>
  <category>
   Handbags
  </category>
  <size>
   L
  </size>
  <color>
   Красный
  </color>
  <material>
   Шелк
  </material>
  <price>
   780234
  </price>
  <rating>
   1.85
  </rating>
  <reviews>
   626442
  </reviews>
  <new>
   -
  </new>
  <exclusive>
   yes
  </exclusive>
  <sporty>
   no
  </sporty>
 </clothing>
 <clothing>
  <id>
   428131370
  </id>
  <name>
   Brooks T-shirt T-5173
  </name>
  <category>
   T-shirt
  </category>
  <size>
   XXL
  </size>
  <color>
   Красный
  </color>
  <material>
   Вискоза
  </material>
  <price>
   269278
  </price>
  <rating>
   1.62
  </rating>
  <reviews>
   763061
  </reviews>
  <new>
   -
  </new>
 </clothing>
 <clothing>
  <id>
   138825960
  </id>
  <name>
   Adidas Shirt T-6976
  </name>
  <category>
   Shirt
  </category>
  <size>
   L
  </size>
  <color>
   Красный
  </color>
  <material>
   Шерсть
  </material>
  <price>
   699255
  </price>
  <rating>
   4.85
  </rating>
  <reviews>
   299348
  </reviews>
  <new>
   -
  </new>
 </clothing>
 <clothing>
  <id>
   946772896
  </id>
  <name>
   PleinSport Hat R-9778
  </name>
  <category>
   Hat
  </category>
  <size>
   XXL
  </size>
  <color>
   Голубой
  </color>
  <material>
   Вискоза
  </material>
  <price>
   317947
  </price>
  <rating>
   3.21
  </rating>
  <reviews>
   214301
  </reviews>
  <exclusive>
   no
  </exclusive>
 </clothing>
 <clothing>
  <id>
   318581340
  </id>
  <name>
   Brooks Sweater H-6022
  </name>
  <category>
   Sweater
  </category>
  <size>
   S
  </size>
  <color>
   Красный
  </color>
  <material>
   Шелк
  </material>
  <price>
   154647
  </price>
  <rating>
   4.45
  </rating>
  <reviews>
   745009
  </reviews>
  <exclusive>
   no
  </exclusive>
 </clothing>
 <clothing>
  <id>
   884844550
  </id>
  <name>
   Reebok Belts Y-1362
  </name>
  <category>
   Belts
  </category>
  <size>
   L
  </size>
  <color>
   Голубой
  </color>
  <material>
   Шелк
  </material>
  <price>
   202262
  </price>
  <rating>
   3.18
  </rating>
  <reviews>
   758500
  </reviews>
  <new>
   -
  </new>
  <exclusive>
   no
  </exclusive>
 </clothing>
 <clothing>
  <id>
   221263638
  </id>
  <name>
   PleinSport Handbags R-9058
  </name>
  <category>
   Handbags
  </category>
  <size>
   S
  </size>
  <color>
   Красный
  </color>
  <material>
   Кожа
  </material>
  <price>
   317463
  </price>
  <rating>
   3.34
  </rating>
  <reviews>
   226865
  </reviews>
  <new>
   -
  </new>
  <exclusive>
   yes
  </exclusive>
 </clothing>
 <clothing>
  <id>
   140315755
  </id>
  <name>
   New Balance Gloves K-5542
  </name>
  <category>
   Gloves
  </category>
  <size>
   M
  </size>
  <color>
   Зеленый
  </color>
  <material>
   Шелк
  </material>
  <price>
   299772
  </price>
  <rating>
   3.14
  </rating>
  <reviews>
   820991
  </reviews>
 </clothing>
 <clothing>
  <id>
   197861518
  </id>
  <name>
   Adidas Sweater R-7578
  </name>
  <category>
   Sweater
  </category>
  <size>
   L
  </size>
  <color>
   Синий
  </color>
  <material>
   Хлопок
  </material>
  <price>
   657689
  </price>
  <rating>
   2.6
  </rating>
  <reviews>
   459371
  </reviews>
  <new>
   -
  </new>
 </clothing>
 <clothing>
  <id>
   762705246
  </id>
  <name>
   Reebok Belts P-3124
  </name>
  <category>
   Belts
  </category>
  <size>
   S
  </size>
  <color>
   Красный
  </color>
  <material>
   Вискоза
  </material>
  <price>
   585551
  </price>
  <rating>
   1.3
  </rating>
  <reviews>
   539301
  </reviews>
  <new>
   -
  </new>
  <exclusive>
   no
  </exclusive>
  <sporty>
   no
  </sporty>
 </clothing>
 <clothing>
  <id>
   880921426
  </id>
  <name>
   Vans Gloves F-5707
  </name>
  <category>
   Gloves
  </category>
  <size>
   L
  </size>
  <color>
   Фиолетовый
  </color>
  <material>
   Шелк
  </material>
  <price>
   585819
  </price>
  <rating>
   4.03
  </rating>
  <reviews>
   392564
  </reviews>
 </clothing>
 <clothing>
  <id>
   817470261
  </id>
  <name>
   PleinSport T-shirt J-3705
  </name>
  <category>
   T-shirt
  </category>
  <size>
   XL
  </size>
  <color>
   Фиолетовый
  </color>
  <material>
   Хлопок
  </material>
  <price>
   881441
  </price>
  <rating>
   3.0
  </rating>
  <reviews>
   748107
  </reviews>
  <new>
   +
  </new>
  <exclusive>
   yes
  </exclusive>
 </clothing>
 <clothing>
  <id>
   817558012
  </id>
  <name>
   Asics Shoes X-3157
  </name>
  <category>
   Shoes
  </category>
  <size>
   L
  </size>
  <color>
   Красный
  </color>
  <material>
   Хлопок
  </material>
  <price>
   485958
  </price>
  <rating>
   3.34
  </rating>
  <reviews>
   83809
  </reviews>
  <exclusive>
   yes
  </exclusive>
  <sporty>
   no
  </sporty>
 </clothing>
 <clothing>
  <id>
   788056602
  </id>
  <name>
   Converse Jeans K-2770
  </name>
  <category>
   Jeans
  </category>
  <size>
   L
  </size>
  <color>
   Красный
  </color>
  <material>
   Вискоза
  </material>
  <price>
   265630
  </price>
  <rating>
   3.28
  </rating>
  <reviews>
   984321
  </reviews>
  <exclusive>
   yes
  </exclusive>
  <sporty>
   no
  </sporty>
 </clothing>
 <clothing>
  <id>
   784240575
  </id>
  <name>
   Fila Sweater W-8725
  </name>
  <category>
   Sweater
  </category>
  <size>
   S
  </size>
  <color>
   Зеленый
  </color>
  <material>
   Кожа
  </material>
  <price>
   181946
  </price>
  <rating>
   4.99
  </rating>
  <reviews>
   960039
  </reviews>
  <exclusive>
   no
  </exclusive>
  <sporty>
   yes
  </sporty>
 </clothing>
 <clothing>
  <id>
   646686274
  </id>
  <name>
   Asics Dress N-8490
  </name>
  <category>
   Dress
  </category>
  <size>
   XL
  </size>
  <color>
   Синий
  </color>
  <material>
   Полиэстер
  </material>
  <price>
   406284
  </price>
  <rating>
   2.56
  </rating>
  <reviews>
   361883
  </reviews>
  <new>
   -
  </new>
  <sporty>
   no
  </sporty>
 </clothing>
 <clothing>
  <id>
   858262185
  </id>
  <name>
   Fila Jeans J-4149
  </name>
  <category>
   Jeans
  </category>
  <size>
   XXL
  </size>
  <color>
   Зеленый
  </color>
  <material>
   Хлопок
  </material>
  <price>
   337484
  </price>
  <rating>
   2.62
  </rating>
  <reviews>
   82014
  </reviews>
  <new>
   -
  </new>
  <exclusive>
   no
  </exclusive>
 </clothing>
 <clothing>
  <id>
   909321761
  </id>
  <name>
   Nike Blouse Z-4306
  </name>
  <category>
   Blouse
  </category>
  <size>
   XXL
  </size>
  <color>
   Красный
  </color>
  <material>
   Кожа
  </material>
  <price>
   245394
  </price>
  <rating>
   1.77
  </rating>
  <reviews>
   833660
  </reviews>
  <new>
   +
  </new>
  <exclusive>
   no
  </exclusive>
  <sporty>
   no
  </sporty>
 </clothing>
 <clothing>
  <id>
   984566316
  </id>
  <name>
   New Balance Pants O-5480
  </name>
  <category>
   Pants
  </category>
  <size>
   L
  </size>
  <color>
   Оранжевый
  </color>
  <material>
   Лен
  </material>
  <price>
   536498
  </price>
  <rating>
   3.06
  </rating>
  <reviews>
   640800
  </reviews>
  <new>
   -
  </new>
  <sporty>
   yes
  </sporty>
 </clothing>
 <clothing>
  <id>
   201239544
  </id>
  <name>
   DC Socks U-4347
  </name>
  <category>
   Socks
  </category>
  <size>
   L
  </size>
  <color>
   Оранжевый
  </color>
  <material>
   Хлопок
  </material>
  <price>
   310093
  </price>
  <rating>
   1.29
  </rating>
  <reviews>
   185520
  </reviews>
  <exclusive>
   no
  </exclusive>
 </clothing>
 <clothing>
  <id>
   686147322
  </id>
  <name>
   Nike Shoes R-4312
  </name>
  <category>
   Shoes
  </category>
  <size>
   S
  </size>
  <color>
   Оранжевый
  </color>
  <material>
   Нейлон
  </material>
  <price>
   391200
  </price>
  <rating>
   3.47
  </rating>
  <reviews>
   252236
  </reviews>
 </clothing>
 <clothing>
  <id>
   615825419
  </id>
  <name>
   Asics Blouse O-4360
  </name>
  <category>
   Blouse
  </category>
  <size>
   XXL
  </size>
  <color>
   Голубой
  </color>
  <material>
   Шелк
  </material>
  <price>
   299538
  </price>
  <rating>
   2.49
  </rating>
  <reviews>
   642524
  </reviews>
  <new>
   -
  </new>
  <sporty>
   yes
  </sporty>
 </clothing>
</clothing-items>
